fancyboxmd.py
fancyboxmd-1.1.0.dist-info/METADATA
fancyboxmd-1.1.0.dist-info/WHEEL
fancyboxmd-1.1.0.dist-info/top_level.txt
fancyboxmd-1.1.0.dist-info/RECORD
