Metadata-Version: 2.1
Name: fancyboxmd
Version: 1.1.0
Summary: Extension for python-markdown that adds markdown syntax for !![image.jpg] for fancybox tag.
Home-page: https://github.com/opengisch/fancyboxmd.git
Author: Matthias Kuhn
Author-email: matthias@opengis.ch
License: MIT
Platform: UNKNOWN
Classifier: License :: OSI Approved :: MIT License
Classifier: Programming Language :: Python :: 3
Classifier: Operating System :: OS Independent
Classifier: Intended Audience :: Developers
Classifier: Topic :: Text Processing :: Markup
Classifier: Topic :: Text Processing :: Markup :: HTML
Requires-Dist: markdown (>=3.0)
